ClassicalSplit/__init__.py
ClassicalSplit/evaluate.py
ClassicalSplit/evaluation.py
ClassicalSplit/langconv.py
ClassicalSplit/seg_eval.py
ClassicalSplit/segmenter.py
ClassicalSplit/setup.py
ClassicalSplit/smseg_eval.py
ClassicalSplit/smseg_helper.py
ClassicalSplit/smseg_model.py
ClassicalSplit/smseg_model_curriculum.py
ClassicalSplit/superloss.py
ClassicalSplit/test.py
ClassicalSplit/transformer.py
ClassicalSplit/use_curriculum.py
ClassicalSplit/utils.py
ClassicalSplit/variables.py
ClassicalSplit/zh_wiki.py
ClassicalSplit/data/__init__.py
ClassicalSplit/data/data.py
ClassicalSplit/logs/__init__.py
ClassicalSplit/model/__init__.py
ClassicalSplit/pytorch_pretrained_bert/__init__.py
ClassicalSplit/pytorch_pretrained_bert/__main__.py
ClassicalSplit/pytorch_pretrained_bert/convert_gpt2_checkpoint_to_pytorch.py
ClassicalSplit/pytorch_pretrained_bert/convert_openai_checkpoint_to_pytorch.py
ClassicalSplit/pytorch_pretrained_bert/convert_tf_checkpoint_to_pytorch.py
ClassicalSplit/pytorch_pretrained_bert/convert_transfo_xl_checkpoint_to_pytorch.py
ClassicalSplit/pytorch_pretrained_bert/crf.py
ClassicalSplit/pytorch_pretrained_bert/crf2.py
ClassicalSplit/pytorch_pretrained_bert/file_utils.py
ClassicalSplit/pytorch_pretrained_bert/modeling.py
ClassicalSplit/pytorch_pretrained_bert/modeling_convert.py
ClassicalSplit/pytorch_pretrained_bert/modeling_gpt2.py
ClassicalSplit/pytorch_pretrained_bert/modeling_openai.py
ClassicalSplit/pytorch_pretrained_bert/modeling_transfo_xl.py
ClassicalSplit/pytorch_pretrained_bert/modeling_transfo_xl_utilities.py
ClassicalSplit/pytorch_pretrained_bert/modeling_word_boundary_crf.py
ClassicalSplit/pytorch_pretrained_bert/optimization.py
ClassicalSplit/pytorch_pretrained_bert/optimization_openai.py
ClassicalSplit/pytorch_pretrained_bert/tokenization.py
ClassicalSplit/pytorch_pretrained_bert/tokenization_chinese_word.py
ClassicalSplit/pytorch_pretrained_bert/tokenization_gpt2.py
ClassicalSplit/pytorch_pretrained_bert/tokenization_openai.py
classicalsplit-1.4.dist-info/METADATA
classicalsplit-1.4.dist-info/WHEEL
classicalsplit-1.4.dist-info/entry_points.txt
classicalsplit-1.4.dist-info/top_level.txt
classicalsplit-1.4.dist-info/RECORD
