Metadata-Version: 2.4
Name: ClassicalSplit
Version: 1.4
Summary: 一个古汉语分词工具
Home-page: https://github.com/tangxuemei1995/Ancient-chinese-segmenter
Author: TANG, Xuemei
License: MIT
Classifier: Programming Language :: Python :: 3
Classifier: License :: OSI Approved :: MIT License
Classifier: Operating System :: OS Independent
Requires-Python: >=3.8
Requires-Dist: torch<2.0,>=1.11
Requires-Dist: huggingface_hub>=0.16.4
Requires-Dist: tqdm
Requires-Dist: pandas
Requires-Dist: requests>=2.30.0
Requires-Dist: boto3
Requires-Dist: requests
Requires-Dist: regex
Requires-Dist: seqeval
Requires-Dist: psutil
Requires-Dist: matplotlib
Dynamic: author
Dynamic: classifier
Dynamic: description
Dynamic: description-content-type
Dynamic: home-page
Dynamic: license
Dynamic: requires-dist
Dynamic: requires-python
Dynamic: summary
